bot/__init__.py
bot/bd_interacting.py
bot/main.py
bot/record.py
mayevsky_chatbot-1.1.3.dist-info/LICENSE
mayevsky_chatbot-1.1.3.dist-info/METADATA
mayevsky_chatbot-1.1.3.dist-info/WHEEL
mayevsky_chatbot-1.1.3.dist-info/top_level.txt
mayevsky_chatbot-1.1.3.dist-info/RECORD
