Metadata-Version: 2.1
Name: mayevsky-chatbot
Version: 1.1.3
Summary: The bot for TheBigMayevsky(https://github.com/someanonimcoder/thebigmayevsky)
Home-page: https://github.com/RedSnail/mayevsky-chatbot
Author: RedSnail, SomeAnonimCoder
Author-email: oleg.demianchenko@gmail.com, glubshev2001@mail.ru
License: UNKNOWN
Platform: UNKNOWN
Requires-Dist: vk-api
